        {
			"id": "66334",
			"poster_id": "6789",
			"poster_name": "Lando Calrissian",
			"poster_company": "Rebel Alliance",
			"poster_occupation": "General",
			"poster_email": "lando@heyubaby.me",
			"poster_img": "http://media.comicbook.com/wp-content/uploads/2012/11/lando-calrissian.jpg",
			"title": "Hate the Empire, click here",
			"type": "part time",
			"start_date": "05/04/2016",
			"end_date": null,
			"location": "Endor Moon",
			"description": "We hate the Empire too, but we also are doing something about it.  We are looking for all types of people to come join the fight.  Don't worrie you don't have to be a Jedi to help."
		}